LICENSE.txt
MANIFEST.in
README.rst
setup.cfg
setup.py
tests.py
Flask_Sijax.egg-info/PKG-INFO
Flask_Sijax.egg-info/SOURCES.txt
Flask_Sijax.egg-info/dependency_links.txt
Flask_Sijax.egg-info/not-zip-safe
Flask_Sijax.egg-info/requires.txt
Flask_Sijax.egg-info/top_level.txt
docs/Makefile
docs/conf.py
docs/index.rst
docs/make.bat
docs/_themes/LICENSE
docs/_themes/README
docs/_themes/flask_theme_support.py
docs/_themes/flask/layout.html
docs/_themes/flask/relations.html
docs/_themes/flask/theme.conf
docs/_themes/flask/static/flasky.css_t
docs/_themes/flask/static/small_flask.css
docs/_themes/flask_small/layout.html
docs/_themes/flask_small/theme.conf
docs/_themes/flask_small/static/flasky.css_t
examples/chat.py
examples/comet.py
examples/hello.py
examples/upload.py
examples/templates/chat.html
examples/templates/comet.html
examples/templates/hello.html
examples/templates/upload.html
flask_sijax/__init__.py