Metadata-Version: 1.0
Name: Flask-Sijax
Version: 0.3.0
Summary: An extension for the Flask microframework that adds Sijax support.
Home-page: https://github.com/spantaleev/flask-sijax
Author: Slavi Pantaleev
Author-email: s.pantaleev@gmail.com
License: BSD
Keywords: ajax,jQuery,flask
Platform: any
Classifier: Programming Language :: Python
Classifier: Development Status :: 4 - Beta
Classifier: Environment :: Web Environment
Classifier: Intended Audience :: Developers
Classifier: License :: OSI Approved :: BSD License
Classifier: Operating System :: OS Independent
Classifier: Topic :: Internet :: WWW/HTTP :: Dynamic Content
Classifier: Topic :: Software Development :: Libraries :: Python Modules
